{
  "ResourceSpecification": "org.openassociation.resourceSpecification",
  "ProcessSpecification": "org.openassociation.processSpecification",
  "Action": "org.openassociation.action",
  "Recipe": "org.openassociation.recipe",
  "RecipeProcess": "org.openassociation.recipeProcess",
  "RecipeFlow": "org.openassociation.recipeFlow",
  "RecipeExchange": "org.openassociation.recipeExchange",
  "SpatialThing": "org.openassociation.spatialThing",
  "Unit": "org.openassociation.unit",
  "Plan": "org.openassociation.plan",
  "Intent": "org.openassociation.intent",
  "Proposal": "org.openassociation.proposal",
  "ProposalList": "org.openassociation.proposalList",
  "Commitment": "org.openassociation.commitment",
  "Agreement": "org.openassociation.agreement",
  "AgreementBundle": "org.openassociation.agreementBundle",
  "Claim": "org.openassociation.claim",
  "Process": "org.openassociation.process",
  "Person": "org.openassociation.person",
  "Organization": "org.openassociation.organization",
  "EcologicalAgent": "org.openassociation.ecologicalAgent",
  "EconomicResource": "org.openassociation.economicResource",
  "EconomicEvent": "org.openassociation.economicEvent",
  "BatchLotRecord": "org.openassociation.batchLotRecord"
}
